mainland-0.0.1.dist-info/metadata.json
mainland-0.0.1.dist-info/METADATA
mainland-0.0.1.dist-info/WHEEL
mainland-0.0.1.dist-info/DESCRIPTION.rst
mainland-0.0.1.dist-info/RECORD
mainland-0.0.1.dist-info/top_level.txt
mainland/__init__.py
mainland/_main.py
mainland/__main__.py
mainland/_version.py
mainland/tests/__init__.py
mainland/tests/nitpicker.py
mainland/tests/dummy1.py
mainland/tests/test_main.py
mainland/tests/functional_test.py
